psyco_full.py
RSeQC-5.0.3.data/scripts/FPKM-UQ.py
RSeQC-5.0.3.data/scripts/FPKM_count.py
RSeQC-5.0.3.data/scripts/RNA_fragment_size.py
RSeQC-5.0.3.data/scripts/RPKM_saturation.py
RSeQC-5.0.3.data/scripts/bam2fq.py
RSeQC-5.0.3.data/scripts/bam2wig.py
RSeQC-5.0.3.data/scripts/bam_stat.py
RSeQC-5.0.3.data/scripts/clipping_profile.py
RSeQC-5.0.3.data/scripts/deletion_profile.py
RSeQC-5.0.3.data/scripts/divide_bam.py
RSeQC-5.0.3.data/scripts/geneBody_coverage.py
RSeQC-5.0.3.data/scripts/geneBody_coverage2.py
RSeQC-5.0.3.data/scripts/infer_experiment.py
RSeQC-5.0.3.data/scripts/inner_distance.py
RSeQC-5.0.3.data/scripts/insertion_profile.py
RSeQC-5.0.3.data/scripts/junction_annotation.py
RSeQC-5.0.3.data/scripts/junction_saturation.py
RSeQC-5.0.3.data/scripts/mismatch_profile.py
RSeQC-5.0.3.data/scripts/normalize_bigwig.py
RSeQC-5.0.3.data/scripts/overlay_bigwig.py
RSeQC-5.0.3.data/scripts/read_GC.py
RSeQC-5.0.3.data/scripts/read_NVC.py
RSeQC-5.0.3.data/scripts/read_distribution.py
RSeQC-5.0.3.data/scripts/read_duplication.py
RSeQC-5.0.3.data/scripts/read_hexamer.py
RSeQC-5.0.3.data/scripts/read_quality.py
RSeQC-5.0.3.data/scripts/sc_bamStat.py
RSeQC-5.0.3.data/scripts/sc_editMatrix.py
RSeQC-5.0.3.data/scripts/sc_seqLogo.py
RSeQC-5.0.3.data/scripts/sc_seqQual.py
RSeQC-5.0.3.data/scripts/split_bam.py
RSeQC-5.0.3.data/scripts/split_paired_bam.py
RSeQC-5.0.3.data/scripts/tin.py
qcmodule/BED.py
qcmodule/FrameKmer.py
qcmodule/SAM.py
qcmodule/__init__.py
qcmodule/annoGene.py
qcmodule/bam_cigar.py
qcmodule/changePoint.py
qcmodule/cigar.py
qcmodule/dotProduct.py
qcmodule/fasta.py
qcmodule/fastq.py
qcmodule/getBamFiles.py
qcmodule/heatmap.py
qcmodule/ireader.py
qcmodule/mystat.py
qcmodule/orf.py
qcmodule/quantile.py
qcmodule/scbam.py
qcmodule/twoList.py
qcmodule/wiggle.py
RSeQC-5.0.3.dist-info/METADATA
RSeQC-5.0.3.dist-info/WHEEL
RSeQC-5.0.3.dist-info/top_level.txt
RSeQC-5.0.3.dist-info/RECORD
